pytk_net/__init__.py
pytk_net/utils.py
pytk_net/widgets.py
pytk_net/ext/__init__.py
pytk_net/ext/ext_tabs.py
pytk_net/ext/icon.py
pytk_net/icons/bootstrap-icons.json
pytk_net/icons/bootstrap-icons.woff
pytk_net/overwrite/DateEntry.py
pytk_net/overwrite/__init__.py
pytk_net-1.0.0.dist-info/METADATA
pytk_net-1.0.0.dist-info/WHEEL
pytk_net-1.0.0.dist-info/top_level.txt
pytk_net-1.0.0.dist-info/RECORD
