Metadata-Version: 2.1
Name: pytk_net
Version: 1.0.0
Summary: TkinterHelper布局助手官方拓展和工具库
Home-page: https://www.pytk.net
Author: iamxcd
Requires-Python: >=3.8
